moneycontrol/ArticleExtractor.py
moneycontrol/__init__.py
moneycontrol/utils/DateParser.py
moneycontrol/utils/__init__.py
moneycontrol-1.0.2.dist-info/METADATA
moneycontrol-1.0.2.dist-info/WHEEL
moneycontrol-1.0.2.dist-info/entry_points.txt
moneycontrol-1.0.2.dist-info/top_level.txt
moneycontrol-1.0.2.dist-info/RECORD
