Metadata-Version: 2.1
Name: moneycontrol
Version: 1.0.2
Summary: Web scraper for moneycontrol.com
Home-page: https://github.com/Avchhikara/moneycontrol
Author: Avnish
Author-email: avnishchhikara@outlook.com
License: MIT
Keywords: moneycontrol,money control,web scraping,scrape articles
Platform: UNKNOWN
Classifier: License :: OSI Approved :: MIT License
Classifier: Programming Language :: Python :: 3
Classifier: Programming Language :: Python :: 3.7
